LICENSE
django_view_composer/__init__.py
django_view_composer/admin.py
django_view_composer/apps.py
django_view_composer/migrations/__init__.py
django_view_composer/models.py
django_view_composer/templatetags/__init__.py
django_view_composer/templatetags/view_composer.py
django_view_composer/tests.py
django_view_composer/views.py
django_view_composer-0.2.1.dist-info/LICENSE
django_view_composer-0.2.1.dist-info/WHEEL
django_view_composer-0.2.1.dist-info/METADATA
django_view_composer-0.2.1.dist-info/RECORD
