Metadata-Version: 2.1
Name: django-view-composer
Version: 0.2.1
Summary: Django template tags to include views inside other views
Home-page: https://github.com/joshiggins/django-view-composer
License: MIT
Author: Josh Higgins
Author-email: josh@joshh.info
Requires-Python: >=3.8,<4.0
Classifier: License :: OSI Approved :: MIT License
Classifier: Programming Language :: Python :: 3
Classifier: Programming Language :: Python :: 3.10
Classifier: Programming Language :: Python :: 3.8
Classifier: Programming Language :: Python :: 3.9
Requires-Dist: Django (>=3.2,<4.0)
Project-URL: Repository, https://github.com/joshiggins/django-view-composer
